[{"DistrictName":"SAHARANPUR","RegistrationNo":1770027036,"RegistrationDate":"9/19/2023","ApplicantName":"PRATAP SINGH","Gender":"M","FatherName":"TUNGAL","MobileNo":9719513265,"DOB":"1/1/1970","AadharNo":458105169845,"ShareRupees":221,"LandDetailName":"0.5 हेक्टेयर से 1 हेक्टेयर तक","LandTypeName":"निजी भूमि","BpacsName":"किसान सेवा  सहकारी समिति लिमिटेड कोटा","NomineeRelationName":"जीवनसाथी","NomineeName":"USHA DEVI","OccupationName":"कृषक","OccupationCategoryName":"","OccupationOther":"","OccupationId":1,"ShareNumber":2,"GramPanchyatName":"KOTA","TehsilName":"Saharanpur","OccupationSubCategoryName":"","VikasKhandName":"BALLIA KHERI","RajasvGramName":"Kota","Address":"KOTA","PinCode":247551,"ModeOfApplication":"Offline"},{"DistrictName":"SAHARANPUR","RegistrationNo":1770026724,"RegistrationDate":"9/19/2023","ApplicantName":"MANGERAM","Gender":"M","FatherName":"RODHA","MobileNo":7830748128,"DOB":"1/1/1956","AadharNo":939328510821,"ShareRupees":221,"LandDetailName":"0.5 हेक्टेयर से 1 हेक्टेयर तक","LandTypeName":"निजी भूमि","BpacsName":"किसान सेवा  सहकारी समिति लिमिटेड कोटा","NomineeRelationName":"जीवनसाथी","NomineeName":"PREMWATI","OccupationName":"कृषक","OccupationCategoryName":"","OccupationOther":"","OccupationId":1,"ShareNumber":2,"GramPanchyatName":"KOTA","TehsilName":"Saharanpur","OccupationSubCategoryName":"","VikasKhandName":"BALLIA KHERI","RajasvGramName":"Kota","Address":"KOTA","PinCode":247551,"ModeOfApplication":"Offline"},{"DistrictName":"SAHARANPUR","RegistrationNo":1770028338,"RegistrationDate":"9/19/2023","ApplicantName":"MUSARRAT","Gender":"M","FatherName":"LUKMAN","MobileNo":7060425991,"DOB":"1/1/1993","AadharNo":240769060221,"ShareRupees":221,"LandDetailName":"","LandTypeName":"","BpacsName":"किसान सेवा  सहकारी समिति लिमिटेड कोटा","NomineeRelationName":"जीवनसाथी","NomineeName":"LUKMAN","OccupationName":"अकृषक","OccupationCategoryName":"अकुशल","OccupationOther":"HOUSE WIFE","OccupationId":2,"ShareNumber":2,"GramPanchyatName":"UMAHI","TehsilName":"Saharanpur","OccupationSubCategoryName":"खेतिहर अन्य","VikasKhandName":"BALLIA KHERI","RajasvGramName":"Umahi","Address":"UMAHI","PinCode":247551,"ModeOfApplication":"Offline"}]
